sort/__init__.py
sort/bubble_sort.py
sort/insertion_sort.py
sort/quick_sort.py
siwp2005_james_sort-0.0.2.dist-info/LICENSE
siwp2005_james_sort-0.0.2.dist-info/METADATA
siwp2005_james_sort-0.0.2.dist-info/WHEEL
siwp2005_james_sort-0.0.2.dist-info/top_level.txt
siwp2005_james_sort-0.0.2.dist-info/RECORD
