Metadata-Version: 2.1
Name: siwp2005-james-sort
Version: 0.0.2
Summary: A collection of sorting algorithms
Home-page: https://github.com/JamesWilsonLie/siwp2005-james-sort
Author: James Wilson Lie
Author-email: jameswl00012@gmail.com
Project-URL: Bug Tracker, https://github.com/JamesWilsonLie/siwp2005-james-sort/issues
Keywords: sorting algorithms
Classifier: Programming Language :: Python :: 3
Classifier: License :: OSI Approved :: MIT License
Requires-Python: >=3.6
License-File: LICENSE
